uniauth_saml2_idp/__init__.py
uniauth_saml2_idp/admin.py
uniauth_saml2_idp/decorators.py
uniauth_saml2_idp/error_views.py
uniauth_saml2_idp/exceptions.py
uniauth_saml2_idp/forms.py
uniauth_saml2_idp/models.py
uniauth_saml2_idp/urls.py
uniauth_saml2_idp/utils.py
uniauth_saml2_idp/views.py
uniauth_saml2_idp/auth/ldap_peoples.py
uniauth_saml2_idp/auth/multildap.py
uniauth_saml2_idp/management/__init__.py
uniauth_saml2_idp/management/commands/__init__.py
uniauth_saml2_idp/management/commands/aacli.py
uniauth_saml2_idp/management/commands/mdquery.py
uniauth_saml2_idp/migrations/0001_initial.py
uniauth_saml2_idp/migrations/0002_auto_20210408_1050.py
uniauth_saml2_idp/migrations/__init__.py
uniauth_saml2_idp/processors/base.py
uniauth_saml2_idp/processors/ldap.py
uniauth_saml2_idp/processors/unical_attributes_generator.py
uniauth_saml2_idp/static/small_textarea.css
uniauth_saml2_idp/static/textarea_autosize.js
uniauth_saml2_idp/templates/uniauth/data_consent.html
uniauth_saml2_idp/templates/uniauth/error.html
uniauth_saml2_idp/templates/uniauth/login.html
uniauth_saml2_idp/templates/uniauth/user_agreement.html
uniauth_saml2_idp-2.0.1.dist-info/AUTHORS
uniauth_saml2_idp-2.0.1.dist-info/LICENSE
uniauth_saml2_idp-2.0.1.dist-info/METADATA
uniauth_saml2_idp-2.0.1.dist-info/WHEEL
uniauth_saml2_idp-2.0.1.dist-info/top_level.txt
uniauth_saml2_idp-2.0.1.dist-info/RECORD
