Metadata-Version: 2.1
Name: uniauth-saml2-idp
Version: 2.0.1
Summary: uniAuth is a Django SAML2 Identity Provider
Home-page: https://github.com/UniversitaDellaCalabria/uniAuth
Author: Giuseppe De Marco, Francesco Filicetti
Author-email: giuseppe.demarco@unical.it, francesco.filicetti@unical.it
License: Apache 2.0
Platform: UNKNOWN
Classifier: Development Status :: 5 - Production/Stable
Classifier: Environment :: Web Environment
Classifier: Framework :: Django
Classifier: Framework :: Django :: 2.2
Classifier: Framework :: Django :: 3.0
Classifier: Framework :: Django :: 3.1
Classifier: Framework :: Django :: 3.2
Classifier: Intended Audience :: Developers
Classifier: License :: OSI Approved :: Apache Software License
Classifier: Operating System :: OS Independent
Classifier: Programming Language :: Python
Classifier: Programming Language :: Python :: 3.6
Classifier: Programming Language :: Python :: 3.7
Classifier: Programming Language :: Python :: 3.8
Classifier: Topic :: Internet :: WWW/HTTP
Classifier: Topic :: Internet :: WWW/HTTP :: WSGI
Classifier: Topic :: Security
Classifier: Topic :: Software Development :: Libraries :: Application Frameworks
License-File: LICENSE
License-File: AUTHORS
Requires-Dist: django (<4.0,>=3.1.1)
Requires-Dist: djangosaml2 (>=1.0.0)
Requires-Dist: pysaml2 (>=6.5.1)
Requires-Dist: cffi
